main.py
jd_docker_generator-1.0.dist-info/METADATA
jd_docker_generator-1.0.dist-info/WHEEL
jd_docker_generator-1.0.dist-info/entry_points.txt
jd_docker_generator-1.0.dist-info/top_level.txt
jd_docker_generator-1.0.dist-info/RECORD
